iebptpch_pds_extractor/__init__.py
iebptpch_pds_extractor/extractor.py
iebptpch_pds_extractor-1.0.2.dist-info/licenses/LICENSE
iebptpch_pds_extractor-1.0.2.dist-info/METADATA
iebptpch_pds_extractor-1.0.2.dist-info/WHEEL
iebptpch_pds_extractor-1.0.2.dist-info/entry_points.txt
iebptpch_pds_extractor-1.0.2.dist-info/top_level.txt
iebptpch_pds_extractor-1.0.2.dist-info/RECORD
