Metadata-Version: 2.4
Name: iebptpch-pds-extractor
Version: 1.0.2
Summary: Extract PDS members from IEBPTPCH output files with support for both ASCII and EBCDIC formats
Home-page: https://github.com/arunkumars-mf/iebptpch-pds-extractor
Author: Arunkumar Selvam
Author-email: Arunkumar Selvam <aruninfy123@gmail.com>
License: MIT
Project-URL: Homepage, https://github.com/arunkumars-mf/iebptpch-pds-extractor
Project-URL: Bug Reports, https://github.com/arunkumars-mf/iebptpch-pds-extractor/issues
Project-URL: Source, https://github.com/arunkumars-mf/iebptpch-pds-extractor
Project-URL: Documentation, https://github.com/arunkumars-mf/iebptpch-pds-extractor#readme
Project-URL: Citation, https://github.com/arunkumars-mf/iebptpch-pds-extractor/blob/main/CITATION.cff
Keywords: mainframe,pds,iebptpch,ebcdic,ascii,extractor,ibm,z/os,mvs
Classifier: Development Status :: 4 - Beta
Classifier: Intended Audience :: Developers
Classifier: Intended Audience :: System Administrators
Classifier: Topic :: Software Development :: Libraries :: Python Modules
Classifier: Topic :: System :: Archiving
Classifier: Topic :: Utilities
Classifier: License :: OSI Approved :: MIT License
Classifier: Programming Language :: Python :: 3
Classifier: Programming Language :: Python :: 3.6
Classifier: Programming Language :: Python :: 3.7
Classifier: Programming Language :: Python :: 3.8
Classifier: Programming Language :: Python :: 3.9
Classifier: Programming Language :: Python :: 3.10
Classifier: Programming Language :: Python :: 3.11
Classifier: Programming Language :: Python :: 3.12
Classifier: Operating System :: OS Independent
Requires-Python: >=3.6
License-File: LICENSE
Dynamic: author
Dynamic: home-page
Dynamic: license-file
Dynamic: requires-python
